{
  "otg": {
    "support": true,
    "cc_detect_support": false
  },
  "usb": {
    "type": "USB_TYPE_C",
    "protocol": "USB_PROTOCOL_2_X"
  },
  "vibrator": {
    "support": false,
    "version": "VERSION_2"
  },
  "charge": {
    "dual_cp_support": false,
    "series_dual_battery_support": false,
    "parallel_dual_battery_support": false,
    "normal_support": true,
    "vooc_support": true,
    "svooc_support": true,
    "pd_support": false,
    "qc_support": false,
    "pps_support": false,
    "ship_mode_support": true,
    "short_id_otp_status_support": false,
    "input_current_now_support": false,
    "qg_vbat_deviation_support": true,
    "em_mode_support": false,
    "charge_spec": {
      "normal": {
        "battery.temp.plugin.delta.range": "[0,50]",
        "battery.voltage.range": "[3500,4550]",
        "high.capacity.battery.voltage.range": "[3850,4550]",
        "battery.temperate.range": "[150,450]",
        "high.capacity.battery.temperate.range": "[150,450]",
        "charger.voltage.range": "[4250,5500]",
        "high.capacity.charger.voltage.range": "[4250,5500]",
        "battery.current.range": "[-2300,-500]",
        "high.capacity.battery.current.range": "[-2300,-200]",
        "charge.battery.level.range": "[0,100]",
        "high.capacity.threshold": 75
      },
      "vooc": {
        "battery.voltage.range": "[3500,4550]",
        "high.capacity.battery.voltage.range": "[3850,4550]",
        "battery.temperate.range": "[150,450]",
        "high.capacity.battery.temperate.range": "[150,450]",
        "charger.voltage.range": "",
        "high.capacity.charger.voltage.range": "",
        "battery.current.range": "[-4500,-2000]",
        "high.capacity.battery.current.range": "[-3500,-1400]",
        "charge.battery.level.range": "[0,100]",
        "check.voocchg.ing": true,
        "high.capacity.threshold": 75
      },
      "svooc": {
        "battery.voltage.range": "[3500,4550]",
        "high.capacity.battery.voltage.range": "[3850,4550]",
        "battery.temperate.range": "[150,450]",
        "high.capacity.battery.temperate.range": "[150,450]",
        "charger.voltage.range": "",
        "high.capacity.charger.voltage.range": "",
        "battery.current.range": "[-6500,-2000]",
        "high.capacity.battery.current.range": "[-5500,-1400]",
        "charge.battery.level.range": "[0,100]",
        "check.voocchg.ing": true,
        "high.capacity.threshold": 75
      }
    }
  },
  "wireless_charge": {
    "bpp_support": false,
    "epp_support": false,
    "air_vooc_support": false,
    "air_svooc_support": false,
    "reverse_support": false,
    "wireless_power_efficieny_support": false,
    "charge_spec": {}
  }
}